{
	"name": "Darkit Old",
	"colors": {
		"foreground": "#e4e7ee",
		"focusBorder": "#777a80",
		"widget.shadow": "#0f121780",
		"activityBar.background": "#1a1d22",
		"activityBar.foreground": "#999ca2",
		"activityBar.inactiveForeground": "#777a8080",
		"activityBarBadge.background": "#64748b",
		"activityBarBadge.foreground": "#f6ffff",
		"activityBar.border": "#00000000",
		"activityBar.activeBackground": "#00000000",
		"sideBar.background": "#0f1217",
		"sideBar.foreground": "#e4e7ee",
		"sideBarSectionHeader.background": "#1a1d22",
		"sideBarSectionHeader.foreground": "#ffffff",
		"sideBarSectionHeader.border": "#0f1217",
		"sideBarTitle.foreground": "#ffffff",
		"sideBar.border": "#00000000",
		"list.inactiveSelectionBackground": "#2d303580",
		"list.inactiveSelectionForeground": "#feffff",
		"list.hoverBackground": "#41444980",
		"list.hoverForeground": "#feffff",
		"list.activeSelectionBackground": "#777a8080",
		"list.activeSelectionForeground": "#feffff",
		"list.dropBackground": "#0f121780",
		"list.highlightForeground": "#feffff",
		"list.focusBackground": "#41444980",
		"list.focusForeground": "#feffff",
		"listFilterWidget.background": "#1a1d22",
		"listFilterWidget.outline": "#0f1217",
		"listFilterWidget.noMatchesOutline": "#a70013",
		"list.warningForeground": "#f59e0b",
		"tree.indentGuidesStroke": "#999ca2",
		"statusBar.background": "#1a1d22",
		"statusBar.foreground": "#e4e7ee",
		"statusBar.border": "#0f1217",
		"statusBar.debuggingBackground": "#0f1217",
		"statusBar.debuggingForeground": "#feffff",
		"statusBar.debuggingBorder": "#0f1217",
		"statusBar.noFolderBackground": "#1a1d22",
		"statusBar.noFolderForeground": "#e4e7ee",
		"statusBar.noFolderBorder": "#0f1217",
		"titleBar.activeBackground": "#1a1d22",
		"titleBar.activeForeground": "#e4e7ee",
		"titleBar.border": "#00000000",
		"titleBar.inactiveBackground": "#1a1d22",
		"titleBar.inactiveForeground": "#e4e7ee",
		"menubar.selectionBackground": "#0f121780",
		"menubar.selectionForeground": "#feffff",
		"menubar.selectionBorder": "#00000000",
		"menu.background": "#1a1d22",
		"menu.foreground": "#e4e7ee",
		"menu.selectionBackground": "#41444980",
		"menu.selectionForeground": "#feffff",
		"menu.selectionBorder": "#00000000",
		"menu.separatorBackground": "#0f121780",
		"menu.border": "#0f121780",
		"button.background": "#64748b",
		"button.foreground": "#ffffff",
		"button.hoverBackground": "#8595ae",
		"button.secondaryBackground": "#2d303580",
		"button.secondaryForeground": "#e4e7ee",
		"textLink.foreground": "#8595ae",
		"input.background": "#0f1217",
		"input.foreground": "#e4e7ee",
		"input.border": "#00000000",
		"input.placeholderForeground": "#999ca2",
		"inputOption.activeBackground": "#1a1d22",
		"inputOption.activeForeground": "#a3b3cc",
		"inputOption.activeBorder": "#a3b3cc",
		"panel.background": "#1a1d22",
		"panel.border": "#0f1217",
		"panelTitle.activeBorder": "#e4e7ee",
		"panelTitle.activeForeground": "#e4e7ee",
		"terminal.selectionBackground": "#41444980",
		"terminal.border": "#0f1217",
		"terminal.foreground": "#e4e7ee",
		"terminal.ansiWhite": "#feffff",
		"terminal.ansiBrightWhite": "#ffffff",
		"terminal.ansiBlack": "#0f1217",
		"terminal.ansiBrightBlack": "#2d3035",
		"terminal.ansiBlue": "#3049ff",
		"terminal.ansiBrightBlue": "#8795ff",
		"terminal.ansiCyan": "#29ffe2",
		"terminal.ansiGreen": "#10b981",
		"terminal.ansiBrightGreen": "#71ffc2",
		"terminal.ansiMagenta": "#e229ff",
		"terminal.ansiBrightMagenta": "#ee82ff",
		"terminal.ansiRed": "#ef4444",
		"terminal.ansiBrightRed": "#ff8b80",
		"terminal.ansiYellow": "#f59e0b",
		"terminal.ansiBrightYellow": "#ffe15d",
		"terminalCursor.background": "#f6ffff",
		"terminalCursor.foreground": "#64748b80",
		"badge.background": "#8595ae",
		"badge.foreground": "#ffffff",
		"editorGroupHeader.border": "#00000000",
		"editorGroupHeader.tabsBackground": "#1a1d22",
		"editorGroupHeader.tabsBorder": "#0f1217",
		"tab.border": "#0f1217",
		"tab.activeBackground": "#2d3035",
		"tab.activeForeground": "#feffff",
		"tab.activeBorder": "#64748b",
		"tab.activeBorderTop": "#00000000",
		"tab.inactiveBackground": "#0f1217",
		"tab.inactiveForeground": "#b7bac1",
		"tab.hoverBackground": "#2d303580",
		"tab.hoverForeground": "#feffff",
		"breadcrumb.background": "#1a1d22",
		"breadcrumb.foreground": "#feffff",
		"breadcrumb.focusForeground": "#f6ffff",
		"scrollbarSlider.background": "#41444980",
		"scrollbarSlider.hoverBackground": "#414449",
		"scrollbarSlider.activeBackground": "#2d303580",
		"scrollbar.shadow": "#0f121780",
		"editorWidget.background": "#1a1d22",
		"editorWidget.foreground": "#e4e7ee",
		"editorWidget.resizeBorder": "#414449",
		"pickerGroup.border": "#0f1217",
		"pickerGroup.foreground": "#8595ae",
		"debugToolBar.background": "#1a1d22",
		"debugToolBar.border": "#0f1217",
		"notifications.background": "#1a1d22",
		"notifications.foreground": "#e4e7ee",
		"notificationLink.foreground": "#64748b",
		"notificationToast.border": "#0f1217",
		"gitDecoration.addedResourceForeground": "#4ddea3",
		"gitDecoration.modifiedResourceForeground": "#ffe15d",
		"gitDecoration.deletedResourceForeground": "#ff6b63",
		"gitDecoration.renamedResourceForeground": "#4ddea3",
		"gitDecoration.stageModifiedResourceForeground": "#ffe15d",
		"gitDecoration.stageDeletedResourceForeground": "#ff6b63",
		"gitDecoration.untrackedResourceForeground": "#4ddea3",
		"gitDecoration.ignoredResourceForeground": "#999ca280",
		"editor.background": "#1a1d22",
		"editor.foreground": "#e4e7ee",
		"editorLineNumber.foreground": "#b7bac180",
		"editorLineNumber.activeForeground": "#a3b3cc",
		"editorCursor.foreground": "#a3b3cc",
		"editorCursor.background": "#f6ffff",
		"editor.selectionBackground": "#999ca28c",
		"editor.inactiveSelectionBackground": "#2d303580",
		"editor.selectionHighlightBackground": "#8595ae80",
		"editor.findMatchBackground": "#41444980",
		"editor.findMatchBorder": "#8595ae",
		"editor.findMatchHighlightBackground": "#999ca280",
		"editor.findRangeHighlightBackground": "#41444980",
		"editor.rangeHighlightBackground": "#41444980",
		"editor.hoverHighlightBackground": "#2d303580",
		"editor.wordHighlightBackground": "#777a8073",
		"editor.lineHighlightBackground": "#2d303580",
		"editorIndentGuide.background": "#2d303580",
		"editorIndentGuide.activeBackground": "#999ca280",
		"editorRuler.foreground": "#000b1f80",
		"editorBracketMatch.background": "#2e3e5380",
		"editorBracketMatch.border": "#64748b",
		"peekViewEditor.background": "#1a1d22",
		"peekView.border": "#0f1217",
		"peekViewResult.background": "#0f1217",
		"peekViewTitle.background": "#0f1217",
		"minimap.findMatchHighlight": "#00ff00",
		"minimap.selectionOccurrenceHighlight": "#d4ffff",
		"minimap.errorHighlight": "#ff6b63",
		"editorOverviewRuler.wordHighlightStrongForeground": "#8595ae",
		"editorOverviewRuler.wordHighlightForeground": "#d4ffff"
	},
	"tokenColors": [
		{
			"name": "Emphasis",
			"scope": ["emphasis"],
			"settings": {
				"fontStyle": "italic"
			}
		},
		{
			"name": "Strong",
			"scope": ["strong"],
			"settings": {
				"fontStyle": "bold"
			}
		},
		{
			"name": "Header",
			"scope": ["header"],
			"settings": {
				"foreground": "#8595ae"
			}
		},
		{
			"name": "Meta Diff",
			"scope": ["meta.diff", "meta.diff.header"],
			"settings": {
				"foreground": "#777a80"
			}
		},
		{
			"name": "Markup Inserted",
			"scope": ["markup.inserted"],
			"settings": {
				"foreground": "#10b981"
			}
		},
		{
			"name": "Markup Deleted | Markup Error",
			"scope": ["markup.deleted", "markup.error"],
			"settings": {
				"foreground": "#ef4444"
			}
		},
		{
			"name": "Markup Changed",
			"scope": ["markup.changed"],
			"settings": {
				"foreground": "#f59e0b"
			}
		},
		{
			"name": "Invalid",
			"scope": ["invalid"],
			"settings": {
				"foreground": "#ef4444",
				"fontStyle": "underline italic"
			}
		},
		{
			"name": "Invalid Deprecated",
			"scope": ["invalid.deprecated"],
			"settings": {
				"foreground": "#ff8b80",
				"fontStyle": "underline italic"
			}
		},
		{
			"name": "Entity Name Filename",
			"scope": ["entity.name.filename"],
			"settings": {
				"foreground": "#ffee40"
			}
		},
		{
			"name": "User-defined class names",
			"scope": ["entity.name.type.class, entity.name.class"],
			"settings": {
				"foreground": "#ffa361"
			}
		},
		{
			"name": "this | super | self | etc.",
			"scope": [
				"keyword.expressions-and-types.swift",
				"keyword.other.this",
				"variable.language",
				"variable.language punctuation.definition.variable.php",
				"variable.other.readwrite.instance.ruby",
				"variable.parameter.function.language.special"
			],
			"settings": {
				"foreground": "#f0abfc",
				"fontStyle": "italic"
			}
		},
		{
			"name": "Inherited classes",
			"scope": ["entity.other.inherited-class"],
			"settings": {
				"foreground": "#ffa361",
				"fontStyle": "italic"
			}
		},
		{
			"name": "Comments",
			"scope": [
				"comment",
				"punctuation.definition.comment",
				"unused.comment",
				"wildcard.comment"
			],
			"settings": {
				"foreground": "#777a80"
			}
		},
		{
			"name": "JSDoc-style keywords",
			"scope": [
				"comment keyword.codetag.notation",
				"comment.block.documentation keyword",
				"comment.block.documentation storage.type.class"
			],
			"settings": {
				"foreground": "#777a80"
			}
		},
		{
			"name": "JSDoc-style types",
			"scope": ["comment.block.documentation entity.name.type"],
			"settings": {
				"foreground": "#777a80",
				"fontStyle": "italic"
			}
		},
		{
			"name": "JSDoc-style type brackets",
			"scope": [
				"comment.block.documentation entity.name.type punctuation.definition.bracket"
			],
			"settings": {
				"foreground": "#777a80"
			}
		},
		{
			"name": "JSDoc-style comment parameters",
			"scope": ["comment.block.documentation variable"],
			"settings": {
				"foreground": "#777a80",
				"fontStyle": "italic"
			}
		},
		{
			"name": "Constants",
			"scope": ["constant"],
			"settings": {
				"foreground": "#56ffb6"
			}
		},
		{
			"name": "Numbers",
			"scope": ["constant.numeric"],
			"settings": {
				"foreground": "#f0abfc"
			}
		},
		{
			"name": "Variable constant",
			"scope": ["variable.other.constant"],
			"settings": {
				"foreground": "#e4e7ee"
			}
		},
		{
			"name": "Constant escape sequences",
			"scope": [
				"constant.character.escape",
				"constant.character.string.escape",
				"constant.regexp"
			],
			"settings": {
				"foreground": "#d0e0fa"
			}
		},
		{
			"name": "HTML tags",
			"scope": ["entity.name.tag"],
			"settings": {
				"foreground": "#8eebec"
			}
		},
		{
			"name": 0,
			"scope": ["entity.other.attribute-name.parent-selector"],
			"settings": {
				"foreground": "#d4ffff"
			}
		},
		{
			"name": "HTML/CSS attribute names",
			"scope": ["entity.other.attribute-name"],
			"settings": {
				"foreground": "#818cf8",
				"fontStyle": "italic"
			}
		},
		{
			"name": "HTML Tag Definition",
			"scope": [
				"punctuation.definition.tag.begin",
				"punctuation.definition.tag.end"
			],
			"settings": {
				"foreground": "#b4ffff"
			}
		},
		{
			"name": "Function names",
			"scope": [
				"entity.name.function",
				"meta.function-call.generic",
				"meta.function-call.object",
				"meta.function-call.php",
				"meta.function-call.static",
				"meta.method-call.java meta.method",
				"meta.method.groovy",
				"support.function.any-method.lua",
				"keyword.operator.function.infix"
			],
			"settings": {
				"foreground": "#53a5ff"
			}
		},
		{
			"name": "Function parameters",
			"scope": [
				"entity.name.variable.parameter",
				"meta.at-rule.function variable",
				"meta.at-rule.mixin variable",
				"meta.function.arguments variable.other.php",
				"meta.selectionset.graphql meta.arguments.graphql variable.arguments.graphql",
				"variable.parameter"
			],
			"settings": {
				"foreground": "#e4e7ee",
				"fontStyle": "italic"
			}
		},
		{
			"name": "Decorators",
			"scope": [
				"meta.decorator variable.other.readwrite",
				"meta.decorator variable.other.property"
			],
			"settings": {
				"foreground": "#d4ffff",
				"fontStyle": "italic"
			}
		},
		{
			"name": "Decorator Objects",
			"scope": ["meta.decorator variable.other.object"],
			"settings": {
				"foreground": "#53a5ff"
			}
		},
		{
			"name": "Keywords",
			"scope": ["keyword", "punctuation.definition.keyword"],
			"settings": {
				"foreground": "#ff6c9a"
			}
		},
		{
			"name": "Keyword 'new'",
			"scope": ["keyword.control.new", "keyword.operator.new"],
			"settings": {
				"foreground": "#ff6c9a",
				"fontStyle": "bold"
			}
		},
		{
			"name": "Generic selectors (CSS/SCSS/Less/Stylus)",
			"scope": ["meta.selector"],
			"settings": {
				"foreground": "#777a80"
			}
		},
		{
			"name": "Language Built-ins",
			"scope": ["support"],
			"settings": {
				"foreground": "#ffa361",
				"fontStyle": "italic"
			}
		},
		{
			"name": "Built-in magic functions and constants",
			"scope": [
				"support.function.magic",
				"support.variable",
				"variable.other.predefined"
			],
			"settings": {
				"foreground": "#f0abfc",
				"fontStyle": ""
			}
		},
		{
			"name": "Built-in functions",
			"scope": ["support.function"],
			"settings": {
				"foreground": "#53a5ff",
				"fontStyle": ""
			}
		},
		{
			"name": "Built-in properties",
			"scope": ["support.type", "support.type.property-name"],
			"settings": {
				"foreground": "#ffa361",
				"fontStyle": ""
			}
		},
		{
			"name": "Json support.type.property-name",
			"scope": ["support.type.property-name.json"],
			"settings": {
				"foreground": "#ff6c9a"
			}
		},
		{
			"name": "Separators (key/value, namespace, inheritance, pointer, hash, slice, etc)",
			"scope": [
				"constant.other.symbol.hashkey punctuation.definition.constant.ruby",
				"entity.other.attribute-name.placeholder punctuation",
				"entity.other.attribute-name.pseudo-class punctuation",
				"entity.other.attribute-name.pseudo-element punctuation",
				"meta.group.double.toml",
				"meta.group.toml",
				"meta.object-binding-pattern-variable punctuation.destructuring",
				"punctuation.colon.graphql",
				"punctuation.definition.block.scalar.folded.yaml",
				"punctuation.definition.block.scalar.literal.yaml",
				"punctuation.definition.block.sequence.item.yaml",
				"punctuation.definition.entity.other.inherited-class",
				"punctuation.function.swift",
				"punctuation.separator.dictionary.key-value",
				"punctuation.separator.hash",
				"punctuation.separator.inheritance",
				"punctuation.separator.key-value",
				"punctuation.separator.key-value.mapping.yaml",
				"punctuation.separator.namespace",
				"punctuation.separator.pointer-access",
				"punctuation.separator.slice",
				"string.unquoted.heredoc punctuation.definition.string",
				"support.other.chomping-indicator.yaml",
				"punctuation.separator.annotation"
			],
			"settings": {
				"foreground": "#56ffb6"
			}
		},
		{
			"name": "Brackets, braces, parens, etc.",
			"scope": [
				"keyword.operator.other.powershell",
				"keyword.other.statement-separator.powershell",
				"meta.brace.round",
				"meta.function-call punctuation",
				"punctuation.definition.arguments.begin",
				"punctuation.definition.arguments.end",
				"punctuation.definition.entity.begin",
				"punctuation.definition.entity.end",
				"punctuation.definition.tag.cs",
				"punctuation.definition.type.begin",
				"punctuation.definition.type.end",
				"punctuation.section.scope.begin",
				"punctuation.section.scope.end",
				"punctuation.terminator.expression.php",
				"storage.type.generic.java",
				"string.template meta.brace",
				"string.template punctuation.accessor"
			],
			"settings": {
				"foreground": "#56ffb6"
			}
		},
		{
			"name": "Variable interpolation operators",
			"scope": [
				"meta.string-contents.quoted.double punctuation.definition.variable",
				"punctuation.definition.interpolation.begin",
				"punctuation.definition.interpolation.end",
				"punctuation.definition.template-expression.begin",
				"punctuation.definition.template-expression.end",
				"punctuation.section.embedded.begin",
				"punctuation.section.embedded.coffee",
				"punctuation.section.embedded.end",
				"punctuation.section.embedded.end source.php",
				"punctuation.section.embedded.end source.ruby",
				"punctuation.definition.variable.makefile"
			],
			"settings": {
				"foreground": "#b1ffff"
			}
		},
		{
			"name": "Keys (serializable languages)",
			"scope": [
				"entity.name.function.target.makefile",
				"entity.name.section.toml",
				"entity.name.tag.yaml",
				"variable.other.key.toml"
			],
			"settings": {
				"foreground": "#ff6c9a"
			}
		},
		{
			"name": "Dates / timestamps (serializable languages)",
			"scope": ["constant.other.date", "constant.other.timestamp"],
			"settings": {
				"foreground": "#ff487d"
			}
		},
		{
			"name": "YAML aliases",
			"scope": ["variable.other.alias.yaml"],
			"settings": {
				"fontStyle": "italic underline",
				"foreground": "#b4ffff"
			}
		},
		{
			"name": "Storage",
			"scope": [
				"storage",
				"meta.implementation storage.type.objc",
				"meta.interface-or-protocol storage.type.objc",
				"source.groovy storage.type.def"
			],
			"settings": {
				"foreground": "#ff6c9a",
				"fontStyle": ""
			}
		},
		{
			"name": "Types",
			"scope": [
				"entity.name.type",
				"keyword.primitive-datatypes.swift",
				"keyword.type.cs",
				"meta.protocol-list.objc",
				"meta.return-type.objc",
				"source.go storage.type",
				"source.groovy storage.type",
				"source.java storage.type",
				"source.powershell entity.other.attribute-name",
				"storage.class.std.rust",
				"storage.type.attribute.swift",
				"storage.type.c",
				"storage.type.core.rust",
				"storage.type.cs",
				"storage.type.groovy",
				"storage.type.objc",
				"storage.type.php",
				"storage.type.haskell",
				"storage.type.ocaml"
			],
			"settings": {
				"fontStyle": "italic",
				"foreground": "#ffa361"
			}
		},
		{
			"name": "Generics, templates, and mapped type declarations",
			"scope": [
				"entity.name.type.type-parameter",
				"meta.indexer.mappedtype.declaration entity.name.type",
				"meta.type.parameters entity.name.type"
			],
			"settings": {
				"foreground": "#fde68a"
			}
		},
		{
			"name": "Modifiers",
			"scope": ["storage.modifier"],
			"settings": {
				"foreground": "#ff6c9a"
			}
		},
		{
			"name": "RegExp string",
			"scope": [
				"string.regexp",
				"constant.other.character-class.set.regexp",
				"constant.character.escape.backslash.regexp"
			],
			"settings": {
				"foreground": "#b4ffff"
			}
		},
		{
			"name": "Non-capture operators",
			"scope": ["punctuation.definition.group.capture.regexp"],
			"settings": {
				"foreground": "#d4ffff"
			}
		},
		{
			"name": "RegExp start and end characters",
			"scope": [
				"string.regexp punctuation.definition.string.begin",
				"string.regexp punctuation.definition.string.end"
			],
			"settings": {
				"foreground": "#ff487d"
			}
		},
		{
			"name": "Character group",
			"scope": ["punctuation.definition.character-class.regexp"],
			"settings": {
				"foreground": "#ff487d"
			}
		},
		{
			"name": "Capture groups",
			"scope": ["punctuation.definition.group.regexp"],
			"settings": {
				"foreground": "#ff487d"
			}
		},
		{
			"name": "Assertion operators",
			"scope": [
				"punctuation.definition.group.assertion.regexp",
				"keyword.operator.negation.regexp"
			],
			"settings": {
				"foreground": "#ff487d"
			}
		},
		{
			"name": "Positive lookaheads",
			"scope": ["meta.assertion.look-ahead.regexp"],
			"settings": {
				"foreground": "#ff487d"
			}
		},
		{
			"name": "Strings",
			"scope": ["string"],
			"settings": {
				"foreground": "#56ffb6"
			}
		},
		{
			"name": "String quotes (temporary vscode fix)",
			"scope": [
				"punctuation.definition.string.begin",
				"punctuation.definition.string.end"
			],
			"settings": {
				"foreground": "#56ffb6"
			}
		},
		{
			"name": "Property quotes (temporary vscode fix)",
			"scope": [
				"punctuation.support.type.property-name.begin",
				"punctuation.support.type.property-name.end"
			],
			"settings": {
				"foreground": "#ff487d"
			}
		},
		{
			"name": "Docstrings",
			"scope": [
				"string.quoted.docstring.multi",
				"string.quoted.docstring.multi.python punctuation.definition.string.begin",
				"string.quoted.docstring.multi.python punctuation.definition.string.end",
				"string.quoted.docstring.multi.python constant.character.escape"
			],
			"settings": {
				"foreground": "#56ffb6"
			}
		},
		{
			"name": "Variables and object properties",
			"scope": [
				"variable",
				"constant.other.key.perl",
				"support.variable.property",
				"variable.other.constant.js",
				"variable.other.constant.ts",
				"variable.other.constant.tsx"
			],
			"settings": {
				"foreground": "#e4e7ee"
			}
		},
		{
			"name": "Destructuring / aliasing reference name (LHS)",
			"scope": [
				"meta.import variable.other.readwrite",
				"meta.variable.assignment.destructured.object.coffee variable"
			],
			"settings": {
				"fontStyle": "italic",
				"foreground": "#e4e7ee"
			}
		},
		{
			"name": "Destructuring / aliasing variable name (RHS)",
			"scope": [
				"meta.import variable.other.readwrite.alias",
				"meta.export variable.other.readwrite.alias",
				"meta.variable.assignment.destructured.object.coffee variable variable"
			],
			"settings": {
				"fontStyle": "normal",
				"foreground": "#e4e7ee"
			}
		},
		{
			"name": "Variable property",
			"scope": ["variable.other.property"],
			"settings": {
				"foreground": "#a5b4fc"
			}
		},
		{
			"name": "Edge cases (foreground color resets)",
			"scope": [
				"constant.other.symbol.hashkey.ruby",
				"keyword.operator.dereference.java",
				"keyword.operator.navigation.groovy",
				"meta.scope.for-loop.shell punctuation.definition.string.begin",
				"meta.scope.for-loop.shell punctuation.definition.string.end",
				"meta.scope.for-loop.shell string",
				"storage.modifier.import",
				"punctuation.section.embedded.begin.tsx",
				"punctuation.section.embedded.end.tsx",
				"punctuation.section.embedded.begin.jsx",
				"punctuation.section.embedded.end.jsx",
				"punctuation.separator.list.comma.css",
				"constant.language.empty-list.haskell"
			],
			"settings": {
				"foreground": "#e4e7ee"
			}
		},
		{
			"name": "Shell variables prefixed with \"$\" (edge case)",
			"scope": ["source.shell variable.other"],
			"settings": {
				"foreground": "#e4e7ee"
			}
		},
		{
			"name": "Powershell constants mistakenly scoped to `support`, rather than `constant` (edge)",
			"scope": ["support.constant"],
			"settings": {
				"fontStyle": "normal",
				"foreground": "#7dffd5"
			}
		},
		{
			"name": "Makefile prerequisite names",
			"scope": ["meta.scope.prerequisites.makefile"],
			"settings": {
				"foreground": "#777a80"
			}
		},
		{
			"name": "SCSS attibute selector strings",
			"scope": ["meta.attribute-selector.scss"],
			"settings": {
				"foreground": "#777a80"
			}
		},
		{
			"name": "SCSS attribute selector brackets",
			"scope": [
				"punctuation.definition.attribute-selector.end.bracket.square.scss",
				"punctuation.definition.attribute-selector.begin.bracket.square.scss"
			],
			"settings": {
				"foreground": "#777a80"
			}
		},
		{
			"name": "Haskell Pragmas",
			"scope": ["meta.preprocessor.haskell"],
			"settings": {
				"foreground": "#777a80"
			}
		},
		{
			"name": "Log file error",
			"scope": ["log.error"],
			"settings": {
				"foreground": "#777a80",
				"fontStyle": "bold"
			}
		},
		{
			"name": "Log file warning",
			"scope": ["log.warning"],
			"settings": {
				"foreground": "#777a80",
				"fontStyle": "bold"
			}
		}
	],
	"semanticHighlighting": true
}
